mdit_py_heading_attrs/__init__.py
mdit_py_heading_attrs/_version.py
mdit_py_heading_attrs/attribute_parser.py
mdit_py_heading_attrs/plugin.py
mdit_py_heading_attrs-1.0.0.dist-info/METADATA
mdit_py_heading_attrs-1.0.0.dist-info/WHEEL
mdit_py_heading_attrs-1.0.0.dist-info/licenses/LICENSE
mdit_py_heading_attrs-1.0.0.dist-info/RECORD
