Metadata-Version: 2.4
Name: mdit-py-heading-attrs
Version: 1.0.0
Summary: markdown-it-py plugin to add ID attribute support to headings
Project-URL: Home, https://github.com/mangoumbrella/mdit-py-heading-attrs
Project-URL: Source, https://github.com/mangoumbrella/mdit-py-heading-attrs
Author-email: Mango Umbrella LLC <hi@mangoumbrella.com>
License-Expression: Apache-2.0
License-File: LICENSE
Keywords: attributes,heading,markdown,markdown-it,plugin
Classifier: Development Status :: 3 - Alpha
Classifier: Intended Audience :: Developers
Classifier: Operating System :: OS Independent
Classifier: Programming Language :: Python
Classifier: Programming Language :: Python :: 3 :: Only
Classifier: Programming Language :: Python :: 3.10
Classifier: Programming Language :: Python :: 3.11
Classifier: Programming Language :: Python :: 3.12
Classifier: Programming Language :: Python :: 3.13
Classifier: Programming Language :: Python :: 3.14
Classifier: Topic :: Software Development :: Libraries :: Python Modules
Classifier: Topic :: Text Processing :: Markup
Requires-Python: >=3.10
Requires-Dist: markdown-it-py>=3.0.0
